tidsreg/__init__.py
tidsreg/__main__.py
tidsreg/api.py
tidsreg/bulk.py
tidsreg/cli.py
tidsreg/cliutils.py
tidsreg/exceptions.py
tidsreg/inspiration.py
tidsreg/models.py
tidsreg/utils.py
tidsreg-0.6.3.dist-info/METADATA
tidsreg-0.6.3.dist-info/WHEEL
tidsreg-0.6.3.dist-info/entry_points.txt
tidsreg-0.6.3.dist-info/RECORD
