Metadata-Version: 2.3
Name: tidsreg
Version: 0.6.3
Summary: Cli and module to register time in the municipality of Copenhagen
Project-URL: Homepage, https://github.com/kwedel/tidsreg
Project-URL: Issues, https://github.com/kwedel/tidsreg/issues
Author-email: Kåre Obel Wedel <kaarewj@gmail.com>
Classifier: License :: OSI Approved :: MIT License
Classifier: Programming Language :: Python :: 3
Requires-Python: >=3.10
Requires-Dist: click>=8.1.7
Requires-Dist: playwright>=1.47.0
